hcrypt/__init__.py
hcrypt-3.data/scripts/pyCrypt
hcrypt-3.dist-info/METADATA
hcrypt-3.dist-info/WHEEL
hcrypt-3.dist-info/top_level.txt
hcrypt-3.dist-info/RECORD
