Metadata-Version: 2.1
Name: hcrypt
Version: 3
Summary: Encrypt and Decrypt files using AES 256
Home-page: https://github.com/htr-tech
Author: HTR-TECH
Author-email: unknown@email.com
License: MIT
Platform: UNKNOWN
Classifier: Programming Language :: Python :: 3
Classifier: Operating System :: OS Independent
Requires-Dist: cryptography
